phylopypruner/__init__.py
phylopypruner/__main__.py
phylopypruner/decontamination.py
phylopypruner/fasta.py
phylopypruner/filtering.py
phylopypruner/gene_partition.py
phylopypruner/log.py
phylopypruner/mask_monophylies.py
phylopypruner/msa.py
phylopypruner/newick.py
phylopypruner/plot.py
phylopypruner/prune_paralogs.py
phylopypruner/report.py
phylopypruner/root.py
phylopypruner/run.py
phylopypruner/sequence.py
phylopypruner/settings.py
phylopypruner/summary.py
phylopypruner/supermatrix.py
phylopypruner/taxonomic_groups.py
phylopypruner/tree_node.py
phylopypruner/tree_stats.py
phylopypruner-1.2.6.dist-info/LICENSE
phylopypruner-1.2.6.dist-info/METADATA
phylopypruner-1.2.6.dist-info/WHEEL
phylopypruner-1.2.6.dist-info/entry_points.txt
phylopypruner-1.2.6.dist-info/top_level.txt
phylopypruner-1.2.6.dist-info/RECORD
