Metadata-Version: 2.1
Name: phylopypruner
Version: 1.2.6
Summary: tree-based orthology inference
Home-page: https://gitlab.com/fethalen/phylopypruner
Author: Felix Thalen
Author-email: felix.thalen@uni-goettingen.de
License: GPL 3
Keywords: orthology inference,orthologs,tree-based,phylogenetics,phylogenomics,orthology
Platform: UNKNOWN
Classifier: Programming Language :: Python :: 3
Classifier: License :: OSI Approved :: GNU General Public License v3 (GPLv3)
Classifier: Operating System :: OS Independent
Classifier: Topic :: Scientific/Engineering :: Bio-Informatics
Requires-Python: >=3.6
License-File: LICENSE
Requires-Dist: setuptools (>=30.3.0)
Requires-Dist: wheel
Requires-Dist: setuptools-scm
